{
  "formatVersion": 1,
  "database": {
    "version": 2,
    "identityHash": "2d53de62a95942d5979d69bcb0f5e442",
    "entities": [
      {
        "tableName": "session_entities",
        "createSql": "CREATE TABLE IF NOT EXISTS `${TABLE_NAME}` (`id` INTEGER PRIMARY KEY AUTOINCREMENT NOT NULL, `exerciseType` TEXT NOT NULL, `analysisMode` TEXT NOT NULL, `modelVariant` TEXT NOT NULL, `recordedAt` INTEGER NOT NULL, `totalDurationMs` INTEGER NOT NULL, `repCount` INTEGER NOT NULL, `rejectedRepCount` INTEGER NOT NULL, `tempoRpm` REAL NOT NULL, `rhythmConsistency` INTEGER NOT NULL, `avgRomDegrees` REAL NOT NULL, `sessionQualityScore` INTEGER NOT NULL, `validHoldMs` INTEGER NOT NULL, `avgBodyLineAngle` REAL NOT NULL)",
        "fields": [
          {
            "fieldPath": "id",
            "columnName": "id",
            "affinity": "INTEGER",
            "notNull": true
          },
          {
            "fieldPath": "exerciseType",
            "columnName": "exerciseType",
            "affinity": "TEXT",
            "notNull": true
          },
          {
            "fieldPath": "analysisMode",
            "columnName": "analysisMode",
            "affinity": "TEXT",
            "notNull": true
          },
          {
            "fieldPath": "modelVariant",
            "columnName": "modelVariant",
            "affinity": "TEXT",
            "notNull": true
          },
          {
            "fieldPath": "recordedAt",
            "columnName": "recordedAt",
            "affinity": "INTEGER",
            "notNull": true
          },
          {
            "fieldPath": "totalDurationMs",
            "columnName": "totalDurationMs",
            "affinity": "INTEGER",
            "notNull": true
          },
          {
            "fieldPath": "repCount",
            "columnName": "repCount",
            "affinity": "INTEGER",
            "notNull": true
          },
          {
            "fieldPath": "rejectedRepCount",
            "columnName": "rejectedRepCount",
            "affinity": "INTEGER",
            "notNull": true
          },
          {
            "fieldPath": "tempoRpm",
            "columnName": "tempoRpm",
            "affinity": "REAL",
            "notNull": true
          },
          {
            "fieldPath": "rhythmConsistency",
            "columnName": "rhythmConsistency",
            "affinity": "INTEGER",
            "notNull": true
          },
          {
            "fieldPath": "avgRomDegrees",
            "columnName": "avgRomDegrees",
            "affinity": "REAL",
            "notNull": true
          },
          {
            "fieldPath": "sessionQualityScore",
            "columnName": "sessionQualityScore",
            "affinity": "INTEGER",
            "notNull": true
          },
          {
            "fieldPath": "validHoldMs",
            "columnName": "validHoldMs",
            "affinity": "INTEGER",
            "notNull": true
          },
          {
            "fieldPath": "avgBodyLineAngle",
            "columnName": "avgBodyLineAngle",
            "affinity": "REAL",
            "notNull": true
          }
        ],
        "primaryKey": {
          "autoGenerate": true,
          "columnNames": [
            "id"
          ]
        },
        "indices": [],
        "foreignKeys": []
      },
      {
        "tableName": "rep_entities",
        "createSql": "CREATE TABLE IF NOT EXISTS `${TABLE_NAME}` (`id` INTEGER PRIMARY KEY AUTOINCREMENT NOT NULL, `sessionId` INTEGER NOT NULL, `repNumber` INTEGER NOT NULL, `durationMs` INTEGER NOT NULL, `minAngle` REAL NOT NULL, `maxAngle` REAL NOT NULL, `qualityScore` INTEGER NOT NULL, `alertsPsv` TEXT NOT NULL, FOREIGN KEY(`sessionId`) REFERENCES `session_entities`(`id`) ON UPDATE NO ACTION ON DELETE CASCADE )",
        "fields": [
          {
            "fieldPath": "id",
            "columnName": "id",
            "affinity": "INTEGER",
            "notNull": true
          },
          {
            "fieldPath": "sessionId",
            "columnName": "sessionId",
            "affinity": "INTEGER",
            "notNull": true
          },
          {
            "fieldPath": "repNumber",
            "columnName": "repNumber",
            "affinity": "INTEGER",
            "notNull": true
          },
          {
            "fieldPath": "durationMs",
            "columnName": "durationMs",
            "affinity": "INTEGER",
            "notNull": true
          },
          {
            "fieldPath": "minAngle",
            "columnName": "minAngle",
            "affinity": "REAL",
            "notNull": true
          },
          {
            "fieldPath": "maxAngle",
            "columnName": "maxAngle",
            "affinity": "REAL",
            "notNull": true
          },
          {
            "fieldPath": "qualityScore",
            "columnName": "qualityScore",
            "affinity": "INTEGER",
            "notNull": true
          },
          {
            "fieldPath": "alertsPsv",
            "columnName": "alertsPsv",
            "affinity": "TEXT",
            "notNull": true
          }
        ],
        "primaryKey": {
          "autoGenerate": true,
          "columnNames": [
            "id"
          ]
        },
        "indices": [
          {
            "name": "index_rep_entities_sessionId",
            "unique": false,
            "columnNames": [
              "sessionId"
            ],
            "orders": [],
            "createSql": "CREATE INDEX IF NOT EXISTS `index_rep_entities_sessionId` ON `${TABLE_NAME}` (`sessionId`)"
          }
        ],
        "foreignKeys": [
          {
            "table": "session_entities",
            "onDelete": "CASCADE",
            "onUpdate": "NO ACTION",
            "columns": [
              "sessionId"
            ],
            "referencedColumns": [
              "id"
            ]
          }
        ]
      },
      {
        "tableName": "workout_entities",
        "createSql": "CREATE TABLE IF NOT EXISTS `${TABLE_NAME}` (`id` INTEGER PRIMARY KEY AUTOINCREMENT NOT NULL, `name` TEXT NOT NULL, `createdAt` INTEGER NOT NULL, `sortOrder` INTEGER NOT NULL)",
        "fields": [
          {
            "fieldPath": "id",
            "columnName": "id",
            "affinity": "INTEGER",
            "notNull": true
          },
          {
            "fieldPath": "name",
            "columnName": "name",
            "affinity": "TEXT",
            "notNull": true
          },
          {
            "fieldPath": "createdAt",
            "columnName": "createdAt",
            "affinity": "INTEGER",
            "notNull": true
          },
          {
            "fieldPath": "sortOrder",
            "columnName": "sortOrder",
            "affinity": "INTEGER",
            "notNull": true
          }
        ],
        "primaryKey": {
          "autoGenerate": true,
          "columnNames": [
            "id"
          ]
        },
        "indices": [],
        "foreignKeys": []
      },
      {
        "tableName": "workout_item_entities",
        "createSql": "CREATE TABLE IF NOT EXISTS `${TABLE_NAME}` (`id` INTEGER PRIMARY KEY AUTOINCREMENT NOT NULL, `workoutId` INTEGER NOT NULL, `exerciseType` TEXT NOT NULL, `sets` INTEGER NOT NULL, `reps` INTEGER NOT NULL, `position` INTEGER NOT NULL, FOREIGN KEY(`workoutId`) REFERENCES `workout_entities`(`id`) ON UPDATE NO ACTION ON DELETE CASCADE )",
        "fields": [
          {
            "fieldPath": "id",
            "columnName": "id",
            "affinity": "INTEGER",
            "notNull": true
          },
          {
            "fieldPath": "workoutId",
            "columnName": "workoutId",
            "affinity": "INTEGER",
            "notNull": true
          },
          {
            "fieldPath": "exerciseType",
            "columnName": "exerciseType",
            "affinity": "TEXT",
            "notNull": true
          },
          {
            "fieldPath": "sets",
            "columnName": "sets",
            "affinity": "INTEGER",
            "notNull": true
          },
          {
            "fieldPath": "reps",
            "columnName": "reps",
            "affinity": "INTEGER",
            "notNull": true
          },
          {
            "fieldPath": "position",
            "columnName": "position",
            "affinity": "INTEGER",
            "notNull": true
          }
        ],
        "primaryKey": {
          "autoGenerate": true,
          "columnNames": [
            "id"
          ]
        },
        "indices": [
          {
            "name": "index_workout_item_entities_workoutId",
            "unique": false,
            "columnNames": [
              "workoutId"
            ],
            "orders": [],
            "createSql": "CREATE INDEX IF NOT EXISTS `index_workout_item_entities_workoutId` ON `${TABLE_NAME}` (`workoutId`)"
          }
        ],
        "foreignKeys": [
          {
            "table": "workout_entities",
            "onDelete": "CASCADE",
            "onUpdate": "NO ACTION",
            "columns": [
              "workoutId"
            ],
            "referencedColumns": [
              "id"
            ]
          }
        ]
      },
      {
        "tableName": "diet_entry_entities",
        "createSql": "CREATE TABLE IF NOT EXISTS `${TABLE_NAME}` (`id` INTEGER PRIMARY KEY AUTOINCREMENT NOT NULL, `localDate` TEXT NOT NULL, `mealType` TEXT NOT NULL, `name` TEXT NOT NULL, `kcal` INTEGER NOT NULL, `loggedAt` INTEGER NOT NULL)",
        "fields": [
          {
            "fieldPath": "id",
            "columnName": "id",
            "affinity": "INTEGER",
            "notNull": true
          },
          {
            "fieldPath": "localDate",
            "columnName": "localDate",
            "affinity": "TEXT",
            "notNull": true
          },
          {
            "fieldPath": "mealType",
            "columnName": "mealType",
            "affinity": "TEXT",
            "notNull": true
          },
          {
            "fieldPath": "name",
            "columnName": "name",
            "affinity": "TEXT",
            "notNull": true
          },
          {
            "fieldPath": "kcal",
            "columnName": "kcal",
            "affinity": "INTEGER",
            "notNull": true
          },
          {
            "fieldPath": "loggedAt",
            "columnName": "loggedAt",
            "affinity": "INTEGER",
            "notNull": true
          }
        ],
        "primaryKey": {
          "autoGenerate": true,
          "columnNames": [
            "id"
          ]
        },
        "indices": [
          {
            "name": "index_diet_entry_entities_localDate",
            "unique": false,
            "columnNames": [
              "localDate"
            ],
            "orders": [],
            "createSql": "CREATE INDEX IF NOT EXISTS `index_diet_entry_entities_localDate` ON `${TABLE_NAME}` (`localDate`)"
          }
        ],
        "foreignKeys": []
      },
      {
        "tableName": "daily_log_entities",
        "createSql": "CREATE TABLE IF NOT EXISTS `${TABLE_NAME}` (`localDate` TEXT NOT NULL, `waterCups` INTEGER NOT NULL, PRIMARY KEY(`localDate`))",
        "fields": [
          {
            "fieldPath": "localDate",
            "columnName": "localDate",
            "affinity": "TEXT",
            "notNull": true
          },
          {
            "fieldPath": "waterCups",
            "columnName": "waterCups",
            "affinity": "INTEGER",
            "notNull": true
          }
        ],
        "primaryKey": {
          "autoGenerate": false,
          "columnNames": [
            "localDate"
          ]
        },
        "indices": [],
        "foreignKeys": []
      }
    ],
    "views": [],
    "setupQueries": [
      "CREATE TABLE IF NOT EXISTS room_master_table (id INTEGER PRIMARY KEY,identity_hash TEXT)",
      "INSERT OR REPLACE INTO room_master_table (id,identity_hash) VALUES(42, '2d53de62a95942d5979d69bcb0f5e442')"
    ]
  }
}